<?xml version="1.0" encoding="utf-8"?>
<optionset Name="fixrm_sheduletype" localizedName="Shedule Type" description="Type of the schedule engine. Default is custom Outlook/CRM like engine. Advanced is Cron expression based on Hang-fire/Cronos implementation">
  <OptionSetType>picklist</OptionSetType>
  <IsGlobal>1</IsGlobal>
  <IntroducedVersion>1.0.0.0</IntroducedVersion>
  <IsCustomizable>1</IsCustomizable>
  <ExternalTypeName></ExternalTypeName>
  <displaynames>
    <displayname description="Shedule Type" languagecode="1033" />
  </displaynames>
  <Descriptions>
    <Description description="Type of the schedule engine. Default is custom Outlook/CRM like engine. Advanced is Cron expression based on Hang-fire/Cronos implementation" languagecode="1033" />
  </Descriptions>
  <options>
    <option value="378280000" ExternalValue="" Color="#0000ff">
      <labels>
        <label description="Default" languagecode="1033" />
      </labels>
      <Descriptions>
        <Description description="" languagecode="1033" />
      </Descriptions>
    </option>
    <option value="378280001" ExternalValue="" Color="#0000ff">
      <labels>
        <label description="Advanced" languagecode="1033" />
      </labels>
      <Descriptions>
        <Description description="" languagecode="1033" />
      </Descriptions>
    </option>
  </options>
</optionset>